{
  "council_file": "25-0900-S50",
  "title": "COMMUNICATION FROM THE BUREAU OF STREET LIGHTING and ORDINANCE OF INTENTION FIRST CONSIDERATION relative to establishing a hearing date for the maintenance of the New Hampshire Avenue and Fountain Avenue No. 1 Street Lighting District.​",
  "district": "CD 13",
  "appearances": [
    {
      "meeting_id": 17407,
      "date": "2025-11-04T18:00:00",
      "section": "Items for which Public Hearings Have Not Been Held - (10 Votes Required for Consideration)",
      "item_number": "(29)",
      "recommendation": "​ ADOPT the report of the Director, Bureau of Street Lighting, dated September 24, 2025, attached to the Council file. PRESENT and ADOPT the accompanying ORDINANCE OF INTENTION setting the date of January 13, 2026 as the hearing date for the maintenance of the New Hampshire Avenue and Fountain Avenue No. 1 Street Lighting District, in accordance with Proposition 218, Articles XIIIC and XIIID of the California Constitution and Government Code Section 53753.​ Fiscal Impact Statement: The Bureau of Street Lighting reports that if adopted, $381.06 will be collected annually starting with tax year 2025-26 that will go into a dedicated street lighting maintenance assessment account for the use in the operation and maintenance of this street lighting system.​ (Board of Public Works Hearing Date: January 7, 2026) Report from Bureau of Street Lighting dated 9-24-35 Attachment to Report dated 9-24-25 - Draft Ordinance of Intention"
    }
  ],
  "attachments": [
    {
      "historyId": "45b642b6-2299-48bc-9c8a-fc82ad57cd0e",
      "text": "Report from Bureau of Street Lighting dated 9-24-35",
      "url": "/api/compilemeetingattachmenthistory/historyattachment/?historyId=45b642b6-2299-48bc-9c8a-fc82ad57cd0e",
      "meeting_id": 17407,
      "has_summary": false
    },
    {
      "historyId": "6e9a735f-1407-4ea2-b1e2-51348966392b",
      "text": "Attachment to Report dated 9-24-25 - Draft Ordinance of Intention",
      "url": "/api/compilemeetingattachmenthistory/historyattachment/?historyId=6e9a735f-1407-4ea2-b1e2-51348966392b",
      "meeting_id": 17407,
      "has_summary": false
    }
  ],
  "first_seen": "2025-11-04T18:00:00",
  "last_seen": "2025-11-04T18:00:00",
  "stats": {
    "total_appearances": 1,
    "total_attachments": 2,
    "attachments_with_summaries": 0
  }
}